README.rst
setup.cfg
setup.py
zutils/__init__.py
zutils.egg-info/PKG-INFO
zutils.egg-info/SOURCES.txt
zutils.egg-info/dependency_links.txt
zutils.egg-info/requires.txt
zutils.egg-info/top_level.txt
zutils/models/__init__.py
zutils/static/js/components/detail.js
zutils/static/js/components/paginator.js
zutils/templates/form.html
zutils/templates/list.html
zutils/views/__init__.py