Metadata-Version: 1.1
Name: zutils
Version: 0.1.6
Summary: Some utils for python dev
Home-page: https://github.com/zwidny/zutils
Author: zwidny
Author-email: 649038269@qq.com
License: BSD
Keywords: python dev utils
Platform: UNKNOWN
Classifier: Development Status :: 3 - Alpha
Classifier: Intended Audience :: Developers
Classifier: Topic :: Software Development :: Build Tools
Classifier: License :: OSI Approved :: BSD License
Classifier: Programming Language :: Python :: 2
